multimodalrouter/__init__.py
multimodalrouter/graph/__init__.py
multimodalrouter/graph/dataclasses.py
multimodalrouter/graph/graph.py
multimodalrouter/graphics/__init__.py
multimodalrouter/graphics/graphicsWrapper.py
multimodalrouter/router/__init__.py
multimodalrouter/router/build.py
multimodalrouter/router/route.py
multimodalrouter/utils/__init__.py
multimodalrouter/utils/preprocessor.py
multimodalrouter-0.1.13.dist-info/licenses/LICENSE.md
multimodalrouter-0.1.13.dist-info/licenses/NOTICE.md
multimodalrouter-0.1.13.dist-info/METADATA
multimodalrouter-0.1.13.dist-info/WHEEL
multimodalrouter-0.1.13.dist-info/entry_points.txt
multimodalrouter-0.1.13.dist-info/top_level.txt
multimodalrouter-0.1.13.dist-info/RECORD
