Metadata-Version: 2.4
Name: multimodalrouter
Version: 0.1.13
Summary: A graph-based routing library for dynamic routing.
Author-email: Tobias Karusseit <karusseittobi@gmail.com>
License: MIT License
Project-URL: Homepage, https://github.com/K-T0BIAS/MultiModalRouter
Project-URL: Repository, https://github.com/K-T0BIAS/MultiModalRouter
Requires-Python: >=3.11
License-File: LICENSE.md
License-File: NOTICE.md
Requires-Dist: colorama>=0.4.6
Requires-Dist: dill>=0.4.0
Requires-Dist: filelock>=3.19.1
Requires-Dist: fsspec>=2025.9.0
Requires-Dist: Jinja2>=3.1.6
Requires-Dist: MarkupSafe>=3.0.2
Requires-Dist: mpmath>=1.3.0
Requires-Dist: networkx>=3.5
Requires-Dist: numpy>=2.3.3
Requires-Dist: pandas>=2.3.2
Requires-Dist: parquet>=1.3.1
Requires-Dist: ply>=3.11
Requires-Dist: pyarrow>=21.0.0
Requires-Dist: python-dateutil>=2.9.0.post0
Requires-Dist: pytz>=2025.2
Requires-Dist: setuptools>=80.9.0
Requires-Dist: six>=1.17.0
Requires-Dist: sympy>=1.14.0
Requires-Dist: thriftpy2>=0.5.3
Requires-Dist: tqdm>=4.67.1
Requires-Dist: typing_extensions>=4.15.0
Requires-Dist: tzdata>=2025.2
Provides-Extra: torch
Requires-Dist: torch>=2.8.0; extra == "torch"
Provides-Extra: dev
Requires-Dist: pytest>=8.0; extra == "dev"
Requires-Dist: plotly>=6.3.0; extra == "dev"
Provides-Extra: plotly
Requires-Dist: plotly>=6.3.0; extra == "plotly"
Dynamic: license-file
